sgdata/__init__.py
sgdata/client.py
sgdata_sdk-0.1.0.dist-info/licenses/LICENSE
sgdata_sdk-0.1.0.dist-info/METADATA
sgdata_sdk-0.1.0.dist-info/WHEEL
sgdata_sdk-0.1.0.dist-info/top_level.txt
sgdata_sdk-0.1.0.dist-info/RECORD
