Metadata-Version: 2.4
Name: sgdata-sdk
Version: 0.1.0
Summary: Python SDK for Singapore Government Data APIs
Author-email: Ong Kong Tat <ongkongtat@example.com>
Maintainer-email: Ong Kong Tat <ongkongtat@example.com>
License: MIT
Project-URL: Homepage, https://github.com/KT-afk/sgdata-sdk-python
Project-URL: Repository, https://github.com/KT-afk/sgdata-sdk-python
Project-URL: Issues, https://github.com/KT-afk/sgdata-sdk-python/issues
Keywords: singapore,data,api,weather,air-quality,carpark
Classifier: Development Status :: 3 - Alpha
Classifier: Intended Audience :: Developers
Classifier: License :: OSI Approved :: MIT License
Classifier: Programming Language :: Python :: 3
Classifier: Programming Language :: Python :: 3.8
Classifier: Programming Language :: Python :: 3.9
Classifier: Programming Language :: Python :: 3.10
Classifier: Programming Language :: Python :: 3.11
Classifier: Programming Language :: Python :: 3.12
Classifier: Topic :: Software Development :: Libraries :: Python Modules
Requires-Python: >=3.8
License-File: LICENSE
Requires-Dist: requests>=2.31.0
Provides-Extra: dev
Requires-Dist: pytest>=7.4.0; extra == "dev"
Requires-Dist: pytest-cov>=4.1.0; extra == "dev"
Requires-Dist: mypy>=1.5.0; extra == "dev"
Requires-Dist: types-requests>=2.31.0; extra == "dev"
Requires-Dist: black>=23.7.0; extra == "dev"
Requires-Dist: ruff>=0.0.286; extra == "dev"
Dynamic: license-file
